projectree/__init__.py
projectree/cli.py
projectree/core.py
projectree-0.1.0.dist-info/METADATA
projectree-0.1.0.dist-info/WHEEL
projectree-0.1.0.dist-info/entry_points.txt
projectree-0.1.0.dist-info/top_level.txt
projectree-0.1.0.dist-info/RECORD
