Metadata-Version: 2.4
Name: projectree
Version: 0.1.0
Summary: Generate a simple project tree excluding ignored directories.
Author-email: Divya Goyal <divyagoyal6224@gmail.com>
License: MIT
Requires-Python: >=3.8
